molo.surveys-8.3.3-py3.6-nspkg.pth
molo/surveys/__init__.py
molo/surveys/adapters.py
molo/surveys/admin.py
molo/surveys/admin_urls.py
molo/surveys/blocks.py
molo/surveys/edit_handlers.py
molo/surveys/forms.py
molo/surveys/models.py
molo/surveys/rules.py
molo/surveys/urls.py
molo/surveys/utils.py
molo/surveys/views.py
molo/surveys/wagtail_hooks.py
molo/surveys/widgets.py
molo/surveys/management/__init__.py
molo/surveys/management/commands/__init__.py
molo/surveys/management/commands/deduplicate_pageview_data.py
molo/surveys/migrations/0001_initial.py
molo/surveys/migrations/0002_allow_multiple_submissions.py
molo/surveys/migrations/0003_surveysindexpage.py
molo/surveys/migrations/0004_create_surveys_index_page.py
molo/surveys/migrations/0005_add_surveys_permissions_to_groups.py
molo/surveys/migrations/0006_molosurveypage_display_survey_directly.py
molo/surveys/migrations/0007_submit_text_percentage_results.py
molo/surveys/migrations/0008_submission_article_yourwords_settings.py
molo/surveys/migrations/0009_homepage_button_text.py
molo/surveys/migrations/0010_personalisablesurvey_personalisablesurveyformfield.py
molo/surveys/migrations/0011_groupmembershiprule_surveysubmissiondatarule.py
molo/surveys/migrations/0012_add_terms_and_conditions_page.py
molo/surveys/migrations/0013_add_streamfield_for_skip_logic.py
molo/surveys/migrations/0014_update_skip_logic.py
molo/surveys/migrations/0015_add_choices_to_skip_logic.py
molo/surveys/migrations/0016_articletagrule.py
molo/surveys/migrations/0017_make_count_positive_integer.py
molo/surveys/migrations/0018_add_combination_rule.py
molo/surveys/migrations/0019_segmentusergroup.py
molo/surveys/migrations/0020_formfield_admin_label.py
molo/surveys/migrations/0021_surveyresponserule.py
molo/surveys/migrations/0022_questionpaginationmixin.py
molo/surveys/migrations/0023_add_page_view_model.py
molo/surveys/migrations/0024_add_molo_page.py
molo/surveys/migrations/0025_add_homepage_introduction.py
molo.surveys-8.3.3.dist-info/LICENSE
molo.surveys-8.3.3.dist-info/METADATA
molo.surveys-8.3.3.dist-info/WHEEL
molo.surveys-8.3.3.dist-info/namespace_packages.txt
molo.surveys-8.3.3.dist-info/top_level.txt
molo.surveys-8.3.3.dist-info/RECORD
