Metadata-Version: 2.1
Name: molo.surveys
Version: 8.3.3
Summary: This is the molo.surveys project.
Home-page: https://github.com/praekelt/molo.surveys
Author: Praekelt Foundation
Author-email: dev@praekeltfoundation.org
License: BSD
Keywords: molo.surveys
Platform: UNKNOWN
Classifier: Intended Audience :: Developers
Classifier: Natural Language :: English
Classifier: Programming Language :: Python :: 3.6
Requires-Dist: molo.core (<9.0.0,>=8.0.0)
Requires-Dist: celery (<4.0)
Requires-Dist: dateparser (<0.8.0,>=0.7.0)
Requires-Dist: django-celery
Requires-Dist: wagtailsurveys (==0.2.0)
Requires-Dist: wagtail-personalisation-molo (~=1.0.3)
Requires-Dist: psycopg2 (==2.7.7)
Requires-Dist: html5lib (==0.9999999)
Requires-Dist: six (==1.12.0)
Requires-Dist: Unidecode (==0.04.16)
